<annotation>
	<folder>6</folder>
	<filename>alab4_alab4_12_frame_31_6.png</filename>
	<path>/home/rootuser/Downloads/Clips/Imgs/alab4/6/alab4_alab4_12_frame_31_6.png</path>
	<source>
		<database>Unknown</database>
	</source>
	<size>
		<width>67</width>
		<height>190</height>
		<depth>3</depth>
	</size>
	<segmented>0</segmented>
	<object>
		<name>4</name>
		<pose>Unspecified</pose>
		<truncated>0</truncated>
		<difficult>0</difficult>
		<bndbox>
			<xmin>32</xmin>
			<ymin>44</ymin>
			<xmax>49</xmax>
			<ymax>64</ymax>
		</bndbox>
	</object>
</annotation>
